arcade_google_sheets/__init__.py
arcade_google_sheets/__main__.py
arcade_google_sheets/constants.py
arcade_google_sheets/converters.py
arcade_google_sheets/enums.py
arcade_google_sheets/models.py
arcade_google_sheets/templates.py
arcade_google_sheets/types.py
arcade_google_sheets/utils.py
arcade_google_sheets/who_am_i_util.py
arcade_google_sheets/tools/__init__.py
arcade_google_sheets/tools/file_picker.py
arcade_google_sheets/tools/read.py
arcade_google_sheets/tools/search.py
arcade_google_sheets/tools/system_context.py
arcade_google_sheets/tools/write.py
arcade_google_sheets-5.1.0.dist-info/METADATA
arcade_google_sheets-5.1.0.dist-info/WHEEL
arcade_google_sheets-5.1.0.dist-info/entry_points.txt
arcade_google_sheets-5.1.0.dist-info/licenses/LICENSE
arcade_google_sheets-5.1.0.dist-info/RECORD
